Osdental/__init__.py
Osdental/BlobStorage/Storage.py
Osdental/BlobStorage/__init__.py
Osdental/Cli/__init__.py
Osdental/Database/__init__.py
Osdental/Decorators/AuditLog.py
Osdental/Decorators/DecryptedData.py
Osdental/Decorators/Deprecated.py
Osdental/Decorators/Grpc.py
Osdental/Decorators/Retry.py
Osdental/Decorators/SqlDataNormalizer.py
Osdental/Decorators/__init__.py
Osdental/Encryptor/Aes.py
Osdental/Encryptor/Argon2.py
Osdental/Encryptor/Bcrypt.py
Osdental/Encryptor/Jwt.py
Osdental/Encryptor/Rsa.py
Osdental/Encryptor/Sha512.py
Osdental/Encryptor/__init__.py
Osdental/Exception/ControlledException.py
Osdental/Exception/__init__.py
Osdental/ExternalHttp/Client.py
Osdental/ExternalHttp/__init__.py
Osdental/Grpc/__init__.py
Osdental/Grpc/Adapter/AuthGrpcAdapter.py
Osdental/Grpc/Adapter/SharedGrpcAdapter.py
Osdental/Grpc/Adapter/__init__.py
Osdental/Grpc/Base/GrpcClientBase.py
Osdental/Grpc/Base/__init__.py
Osdental/Grpc/Client/AuthGrpcClient.py
Osdental/Grpc/Client/GrpcConnection.py
Osdental/Grpc/Client/SharedGrpcClient.py
Osdental/Grpc/Client/__init__.py
Osdental/Grpc/Generated/Auth_pb2.py
Osdental/Grpc/Generated/Auth_pb2_grpc.py
Osdental/Grpc/Generated/Common_pb2.py
Osdental/Grpc/Generated/Common_pb2_grpc.py
Osdental/Grpc/Generated/Shared_pb2.py
Osdental/Grpc/Generated/Shared_pb2_grpc.py
Osdental/Grpc/Generated/__init__.py
Osdental/Helpers/AuditLogHelper.py
Osdental/Helpers/AuditQueueHelper.py
Osdental/Helpers/DecryptedHelper.py
Osdental/Helpers/EncryptorHelper.py
Osdental/Helpers/RequestHelper.py
Osdental/Helpers/__init__.py
Osdental/InternalHttp/Request.py
Osdental/InternalHttp/Response.py
Osdental/InternalHttp/__init__.py
Osdental/Messaging/AuditServiceBus.py
Osdental/Messaging/AzureServiceBus.py
Osdental/Messaging/Kafka.py
Osdental/Messaging/RabbitMQ.py
Osdental/Messaging/__init__.py
Osdental/Models/Encryptor.py
Osdental/Models/GrpcResponse.py
Osdental/Models/Legacy.py
Osdental/Models/Response.py
Osdental/Models/ShardResource.py
Osdental/Models/Token.py
encryptors-2.21.dist-info/METADATA
encryptors-2.21.dist-info/WHEEL
encryptors-2.21.dist-info/entry_points.txt
encryptors-2.21.dist-info/top_level.txt
encryptors-2.21.dist-info/RECORD
